list_files/__init__.py
list_files/duplicated.py
list_files/physical_data.py
list_files/report_data.py
list_files/report_file.py
list_files/report_name.py
list_files/rootpath.py
tests/__init__.py
tests/test_duplicated_files.py
tests/test_filename.py
tests/test_single_file.py
report_files-0.2.2.dist-info/LICENSE.md
report_files-0.2.2.dist-info/METADATA
report_files-0.2.2.dist-info/WHEEL
report_files-0.2.2.dist-info/top_level.txt
report_files-0.2.2.dist-info/RECORD
