Metadata-Version: 2.1
Name: report-files
Version: 0.2.2
Summary: It creates one files with some data about every files insidea directory (and sub), and a report abotu duplicated files
Home-page: https://github.com/alepuzio/listfiles
Author: Alessandro Puzielli
Author-email: alessandro.puzielli@alepuzio.net
License: UNKNOWN
Platform: UNKNOWN
Classifier: Programming Language :: Python :: 3
Classifier: License :: OSI Approved :: MIT License
Classifier: Operating System :: OS Independent
